pylab_sdk/__init__.py
pylab_sdk/keg.py
pylab_sdk-1.7.1.dist-info/LICENSE
pylab_sdk-1.7.1.dist-info/METADATA
pylab_sdk-1.7.1.dist-info/WHEEL
pylab_sdk-1.7.1.dist-info/top_level.txt
pylab_sdk-1.7.1.dist-info/RECORD
