Metadata-Version: 2.1
Name: pylab-sdk
Version: 1.7.1
Summary: A development kit that collects simple utilities.
Home-page: https://github.com/PyLabCo/pylab-sdk
Author: CHIDA
Author-email: iam.yeongbin.jo@gmail.com
License: MIT
Keywords: python
Classifier: Development Status :: 5 - Production/Stable
Classifier: Topic :: Software Development :: Testing
Classifier: Topic :: System :: Installation/Setup
Classifier: Topic :: Software Development :: Libraries :: Python Modules
Classifier: License :: OSI Approved :: MIT License
Classifier: Programming Language :: Python :: 3
Classifier: Programming Language :: Python :: 3.9
Classifier: Programming Language :: Python :: 3.10
Classifier: Programming Language :: Python :: 3.11
Classifier: Programming Language :: Python :: 3.12
Requires-Python: >=3
License-File: LICENSE
Requires-Dist: requests
